jupyter_ai/_version.py
calliope_jupyter_ai-1.1.1.data/data/share/jupyter/labextensions/@calliope-jupyter-ai/core/install.json
calliope_jupyter_ai-1.1.1.dist-info/METADATA
calliope_jupyter_ai-1.1.1.dist-info/WHEEL
calliope_jupyter_ai-1.1.1.dist-info/entry_points.txt
calliope_jupyter_ai-1.1.1.dist-info/licenses/LICENSE
calliope_jupyter_ai-1.1.1.dist-info/RECORD
